{"bundle_id": "com.pulandres.bazzi", "name": "Bazzi k", "version": "2.0.4", "tagline": "The ultimate iPhone X battery icon customizer tweak.", "homepage": "https://docsystem.github.io/pulandres-mirror","developer": {"name": "Pulandres", "email": ""}, "maintainer": {"name": "Pulandres", "email": ""}, "social": [{"name": "Website", "url": "https://docsystem.github.io/pulandres-mirror"}],"section": "Tweaks", "pre_dependencies": "", "dependencies": "mobilesubstrate, preferenceloader, ws.hbang.common, com.rpetrich.rocketbootstrap (>= 1.0.7~beta1)", "conflicts": "com.neinzedd9.percentagebatteryx, com.neinzedd9.percentagecirclex", "replaces": "com.neinzedd9.percentagebatteryx, com.neinzedd9.percentagecirclex", "provides": "", "other_control": ["Tag: role::enduser", "SomeOtherEntryToControl: True"], "tint": "#55c6d3", "works_min": "11.0", "works_max": "13.5", "featured": "true", "source": "", "changelog": [{"version": "2.0.4", "changes": "Pulandres mirror repo"}]}